flask_ipernity/__init__.py
flask_ipernity/_version.py
flask_ipernity/cache.py
flask_ipernity/callback.py
flask_ipernity/ext.py
flask_ipernity/login.py
Flask_Ipernity-0.1.0.dist-info/LICENSE
Flask_Ipernity-0.1.0.dist-info/METADATA
Flask_Ipernity-0.1.0.dist-info/WHEEL
Flask_Ipernity-0.1.0.dist-info/top_level.txt
Flask_Ipernity-0.1.0.dist-info/RECORD
